{
  "reference_horse": {
    "name": "ダンスインザダーク",
    "base_score": 100,
    "description": "Dロジック指数の基準馬（内部基準のため、ユーザーには表示しない）"
  },
  "scoring_weights": {
    "distance_aptitude": 0.12,
    "bloodline_evaluation": 0.10,
    "jockey_compatibility": 0.08,
    "trainer_evaluation": 0.08,
    "track_aptitude": 0.10,
    "weather_aptitude": 0.06,
    "popularity_factor": 0.08,
    "weight_impact": 0.08,
    "horse_weight_impact": 0.08,
    "corner_specialist": 0.08,
    "margin_analysis": 0.08,
    "time_index": 0.06
  },
  "reference_data": {
    "distance_aptitude": {
      "1400m": 75,
      "1600m": 85,
      "1800m": 95,
      "2000m": 100,
      "2200m": 90,
      "2400m": 85
    },
    "bloodline_evaluation": {
      "sunday_silence_line": 95,
      "northern_dancer_line": 90,
      "storm_cat_line": 85,
      "other": 70
    },
    "jockey_compatibility": {
      "top_jockey": 95,
      "experienced_jockey": 85,
      "average_jockey": 75,
      "rookie_jockey": 65
    },
    "trainer_evaluation": {
      "top_trainer": 90,
      "experienced_trainer": 80,
      "average_trainer": 70,
      "new_trainer": 60
    },
    "track_aptitude": {
      "turf_good": 100,
      "turf_soft": 85,
      "turf_heavy": 70,
      "dirt_good": 80,
      "dirt_soft": 75,
      "dirt_heavy": 70
    },
    "weather_aptitude": {
      "sunny": 100,
      "cloudy": 95,
      "light_rain": 85,
      "heavy_rain": 75
    }
  },
  "calculation_parameters": {
    "confidence_thresholds": {
      "high": 85,
      "medium": 70,
      "low": 0
    },
    "score_normalization": {
      "min_score": 0,
      "max_score": 100,
      "baseline": 70
    }
  },
  "display_settings": {
    "user_facing_name": "Dロジック",
    "hide_reference_horse": true,
    "show_total_score_only": false,
    "decimal_places": 1
  }
} 